{
  "metric": "points",
  "tier": {
    "weapon": 12,
    "ability": 4,
    "armor": 12,
    "ring": 4
  },
  "bannedItems": {
    "weapon": [
      "Bone Dagger",
      "Demon Blade",
      "Sword of Illumination",
      "Void Blade",
      "Sprite Wand",
      "Wand of the Bulwark",
      "Eternal Snowflake Wand",
      "St. Abraham's Wand",
      "Arcane Rapier",
      "Staff of the Crystal Serpent",
      "Poison Fang Dagger",
      "Queen's Stinger",
      "Corrosion Cutter",
      "Staff of Extreme Prejudice",
      "Staff of Iceblast",
      "Ancient Stone Sword",
      "Acidic Slasher",
      "Eternal Graved Great Sword",
      "Crystal Sword",
      "Enchanted Ice Blade",
      "Spirit Staff",
      "Foramite Staff",
      "Indomptable",
      "Bramble Bow",
      "Staff of Esben",
      "Carved Golem Remains",
      "Maize Machete",
      "Soulcursed Scythe",
      "Quartz Cutter",
      "Wand of Geb",
      "Dalvar's Battle Axe",
      "Swashbuckler's Sickle",
      "Savage Claws",
      "Staff of Eruption",
      "Brilliance Bow",
      "Mister Mango",
      "Butter Bow",
      "K.I.D.D. Force",
      "Caduceus of Current Craziness",
      "MMace MMurderer",
      "Blade of Ages",
      "Useless Katana",
      "Sunshine Shiv",
      "Robobow",
      "KoalaPOW",
      "Spicy Wand of Spice",
      "Doctor Swordsworth",
      "Arbiter's Wrath",
      "Prismatic Slasher",
      "Clover Bow",
      "Staff of the Saint",
      "Rainbow Rod",
      "Sword of the Rainbow's End",
      "Katana of Good Fortune",
      "Heartfind Dagger",
      "Cupid's Bow",
      "Staff of Adoration",
      "Wand of Budding Romance",
      "Vinesword",
      "Diamond-Bladed Katana",
      "Dagger of the Terrible Talon",
      "An Icicle",
      "Bow of Nightmares",
      "Staff of Horrific Knowledge",
      "Staff of Yuletide Carols",
      "Present Dispensing Wand",
      "Wand of Ancient Terror",
      "Frostbite"
    ],
    "ability": [
      "Honey Scepter",
      "Cracked Crystal Skull",
      "Hanagasaku",
      "Tome of Pain",
      "Cocoon Quiver",
      "Quintessential Quiver",
      "Mirror Cloak",
      "Archerang",
      "Spelling Spell",
      "Tome of Moral Support",
      "Challenger Helm",
      "Shield of Pogmur",
      "Seal of Eternal Life",
      "Lightning in a Bottle",
      "Epiphany Skull",
      "Helium Trap",
      "Karma Orb",
      "Fool's Prism",
      "Honey Scepter Supreme",
      "Unshuriken",
      "NSFWakizashi",
      "Lullaby",
      "Recursion Mace",
      "Paper Machete",
      "Painbow",
      "Clover Star"
    ],
    "armor": [
      "Chasuble of Holy Light",
      "Snakeskin Armor",
      "Robe of the Tlatoani",
      "Candy-Coated Armor",
      "Woodland Robe",
      "Tlatoani's Shroud",
      "Magic Protective Matrix",
      "Heavy Protective Matrix",
      "Fitted Protective Matrix",
      "Luxurious Leather",
      "Cheater Light Armor",
      "Cheater Robe",
      "Cheater Heavy Armor"
    ],
    "ring": [
      "Crystal Bone Ring",
      "Snake Eye Ring",
      "Candy Ring",
      "Corsair Ring",
      "Spider's Eye Ring",
      "Laborer's Hard Hat",
      "Ornaments of Unity",
      "Loaded Core",
      "First Mate's Hook",
      "Regal Ring"
    ]
  },
  "required points":{
    "Rogue":4,
    "Archer":4,
    "Wizard":4,
    "Priest":4,
    "Warrior":4,
    "Knight":4,
    "Paladin":4,
    "Assassin":4,
    "Necromancer":4,
    "Huntress":4,
    "Mystic":4,
    "Trickster":4,
    "Sorcerer":4,
    "Ninja":4,
    "Samurai":4,
    "Bard":4,
    "Summoner":4,
    "Kensei":4
  },
  "items":{
    "1":{
      "weapon":[
        "Sword of Majesty",
        "Gravelord's Flail",
        "Divinity",
        "Sword of the Colossus",
        "Staff of the Fundamental Core",
        "Spellblade of the Everlasting Death",
        "Superior",
        "Shaman's Staff",
        "Lumiaire",
        "Wand of Retribution",
        "Dusky Catalyst",
        "Kusanagi",
        "Celestial Blade",
        "Arashi",
        "Enforcer",
        "Valor",
        "Dagger of Dire Hatred",
        "Dirk of Cronus",
        "Avarice",
        "Bow of Deep Enchantment",
        "Bow of the Void",
        "Warmonger"
      ],
      "ability":[
        "Helm of the Tribune",
        "Vanguard's Visage",
        "Shield of Orcish Regalia",
        "Shield of Ogmur",
        "Oryx's Escutcheon",
        "Seal of Invocation",
        "Marble Seal",
        "Demon Lord's Skull",
        "Skull of Corrupted Souls",
        "Memento Mori",
        "Orb of Aether",
        "Primal Arcana",
        "Orb of Conflict",
        "Orb of Terror",
        "Penetrating Blast Spell",
        "Recurring Terror Spell",
        "Tablet of the King's Avatar",
        "Genesis Spell",
        "Scepter of the Firmament",
        "Cnidaria Rod",
        "Scepter of Devastation",
        "Scepter of Fulmination",
        "Storm Caller",
        "Tome of the Mushroom Tribes",
        "Chaotic Scripture",
        "Peacekeeper",
        "Incubation Mace",
        "Sentinel's Sidearm",
        "Virtuous Wakizashi",
        "Crystalline Kunai",
        "Kageboshi",
        "Rage Claws",
        "Kaiken",
        "Irradiance Sheath",
        "Prism of Reveries",
        "Prism of Shattered Light",
        "Gambler's Fate",
        "Cloak of Nightmares",
        "Cloak of Bloody Surprises",
        "Cloak of Eerie Trepidation",
        "Crystallised Fang's Venom",
        "Polarity Poison",
        "Wavecrest Concertina",
        "Noble Mandolin",
        "Quiver of the Autumn King",
        "Quiver of the Shadows",
        "Trap of the Vile Spirit",
        "Trap of the Blood Spirit",
        "Cave Dweller Trap"
      ],
      "armor":[
        "Gladiator Guard",
        "Mercy's Bane",
        "Hirejou Tenne",
        "Leviathan Armor",
        "Centaur's Shielding",
        "Vesture of Duality",
        "Robe of the Ancient Intellect",
        "Diplomatic Robe"
      ],
      "ring": [
        "Chrysalis of Eternity",
        "The Forgotten Crown",
        "Ice Crown",
        "Magical Lodestone",
        "Omnipotence Ring"
      ],
      "Exalted God's Horn": {
        "class": [
          "Necromancer",
          "Mystic",
          "Wizard",
          "Sorcerer",
          "Priest",
          "Summoner",
          "Bard",
          "Archer",
          "Huntress"
        ]
      },
      "Chancellor's Cranium": {
        "class": [
          "Warrior",
          "Knight",
          "Paladin",
          "Samurai",
          "Kensei"
        ]
      },
      "Collector's Monocle": {
        "class": [
          "Rogue"
        ]
      },
      "The Twilight Gemstone": {
        "class": [
          "Sorcerer"
        ],
        "ability": [
          "Oryx's Escutcheon",
          "Chaotic Scripture",
          "Rage Claws",
          "Kageboshi",
          "Wavecrest Concertina",
          "Noble Mandolin",
          "Polarity Poison",
          "Primal Arcana",
          "Sentinel's Sidearm",
          "Quiver of the Shadows"
        ]
      }
    }
  }
}
